Workbook

Sheet SCNs
A1: Area | B1: Scene | C1: Who | D1: Shown when | E1: Japanese | F1: JP_Len | G1: English | H1: EN_Len | I1: Comments | J1: Filename | K1: Offset
B2: 00IPL #1 | E2: はるか昔 | F2: =LEN(E2) | G2: Long ago... | H2: =LEN(G2) | J2: 00IPL.SCN | K2: 0x00082
B3: 00IPL #1 | E3: その漆黒の竜は多くの国を焼きつくし | F3: =LEN(E3) | G3: The infernal black dragon arose to incinerate many kingdoms. | H3: =LEN(G3) | J3: 00IPL.SCN | K3: 0x000c3
B4: 00IPL #1 | E4: 幾千もの人の肉を喰らった | F4: =LEN(E4) | G4: The beast feasted on the flesh of countless thousands. | H4: =LEN(G4) | J4: 00IPL.SCN | K4: 0x00111
B5: 00IPL #2 | E5: 比類なき腕を誇った勇者の剣も | F5: =LEN(E5) | G5: The legendary blade wielded by a powerful warrior... | H5: =LEN(G5) | J5: 00IPL.SCN | K5: 0x0018f
B6: 00IPL #2 | E6: 偉大なる魔導師の天地を揺るがす魔法も | F6: =LEN(E6) | G6: Magic that could tear heaven asunder cast by a powerful mage... | H6: =LEN(G6) | J6: 00IPL.SCN | K6: 0x001de
B7: 00IPL #2 | E7: 聖なる神の力を具現する高僧の祈りも | F7: =LEN(E7) | G7: The holiest prayers of a high priest imbued by God... | H7: =LEN(G7) | J7: 00IPL.SCN | K7: 0x00231
B8: 00IPL #2 | E8: 彼の者には通用せず | F8: =LEN(E8) | G8: None were effective. | H8: =LEN(G8) | J8: 00IPL.SCN | K8: 0x00283
B9: 00IPL #2 | E9: 追い詰められた人々は、ついに魔を以て、これを打ち倒さんとした | F9: =LEN(E9) | G9: Finally those tormented by the beast turned to demonic powers to defeat the dragon. | H9: =LEN(G9) | J9: 00IPL.SCN | K9: 0x002cd
B10: 00IPL #3 | E10: 滅ぼせぬもの無き武器を | F10: =LEN(E10) | G10: Weapons with truly unstoppable power... | H10: =LEN(G10) | J10: 00IPL.SCN | K10: 0x0035e
B11: 00IPL #3 | E11: この世のものにあらざる武器を | F11: =LEN(E11) | G11: Weapons not of this world. | H11: =LEN(G11) | J11: 00IPL.SCN | K11: 0x003aa
B12: 00IPL #4 | E12: ・・・そして | F12: =LEN(E12) | G12: Until... | H12: =LEN(G12) | J12: 00IPL.SCN | K12: 0x0042b
B13: 00IPL #4 | E13: 一振の剣が造られたのである | F13: =LEN(E13) | G13: ...one single sword was forged. | H13: =LEN(G13) | I13: After this the title shows the name of the sword. | J13: 00IPL.SCN | K13: 0x00472
B14: 00IPL #5 | F14: =LEN(E14) | G14: [BLANK] | H14: =LEN(G14) | J14: 00IPL.SCN | K14: 0x00551
B15: 00IPL #5 | E15: ・・・これは | F15: =LEN(E15) | G15: Is this... | H15: =LEN(G15) | J15: 00IPL.SCN | K15: 0x0056e
B16: 00IPL #5 | F16: =LEN(E16) | G16: [BLANK] | H16: =LEN(G16) | J16: 00IPL.SCN | K16: 0x00582
B17: 00IPL #5 | E17: ・・・おれの乗っていた船か？ | F17: =LEN(E17) | G17: ...is it the ship I was traveling on? | H17: =LEN(G17) | J17: 00IPL.SCN | K17: 0x00597
B18: 00IPL #5 | F18: =LEN(E18) | G18: [BLANK] | H18: =LEN(G18) | J18: 00IPL.SCN | K18: 0x005c2
B19: 00IPL #5 | E19: 静かで、雨の一滴も降らぬ嵐でした。 | F19: =LEN(E19) | G19: That quiet storm, with not a drop of rain... | H19: =LEN(G19) | J19: 00IPL.SCN | K19: 0x005d4
B20: 00IPL #5 | F20: =LEN(E20) | G20: [BLANK] | H20: =LEN(G20) | J20: 00IPL.SCN | K20: 0x005fe
B21: 00IPL #5 | E21: 凡庸な感想ですが、 | F21: =LEN(E21) | G21: Any explanation is inadequate, but... | H21: =LEN(G21) | J21: 00IPL.SCN | K21: 0x00618
B22: 00IPL #5 | F22: =LEN(E22) | G22: [BLANK] | H22: =LEN(G22) | J22: 00IPL.SCN | K22: 0x00632
B23: 00IPL #5 | E23: 奇妙な・・・としか言い様がありません。 | F23: =LEN(E23) | G23: it was truly bizarre... no words can describe it. | H23: =LEN(G23) | J23: 00IPL.SCN | K23: 0x00642
B24: 00IPL #5 | F24: =LEN(E24) | G24: [BLANK] | H24: =LEN(G24) | J24: 00IPL.SCN | K24: 0x00670
B25: 00IPL #5 | E25: あのような嵐は、土地の古老でさえ、 | F25: =LEN(E25) | G25: It was the first time that anyone, | H25: =LEN(G25) | J25: 00IPL.SCN | K25: 0x00682
B26: 00IPL #5 | F26: =LEN(E26) | G26: [BLANK] | H26: =LEN(G26) | J26: 00IPL.SCN | K26: 0x006ac
B27: 00IPL #5 | E27: 目にするのは初めてだったことでしょう。 | F27: =LEN(E27) | G27: even the elders of the land, had seen such a storm. | H27: =LEN(G27) | J27: 00IPL.SCN | K27: 0x006bc
B28: 00IPL #5 | F28: =LEN(E28) | G28: [BLANK] | H28: =LEN(G28) | J28: 00IPL.SCN | K28: 0x006f1
B29: 00IPL #5 | E29: 手荒い歓迎だったな。 | F29: =LEN(E29) | G29: It was a violent welcome. | H29: =LEN(G29) | J29: 00IPL.SCN | K29: 0x0070a
B30: 00IPL #5 | F30: =LEN(E30) | G30: [BLANK] | H30: =LEN(G30) | J30: 00IPL.SCN | K30: 0x00726
B31: 00IPL #5 | E31: どうやら、おれはこの国に嫌われてるらしい | F31: =LEN(E31) | G31: It would seem this country already despises me... | H31: =LEN(G31) | J31: 00IPL.SCN | K31: 0x00735
B32: 00IPL #5 | F32: =LEN(E32) | G32: [BLANK] | H32: =LEN(G32) | J32: 00IPL.SCN | K32: 0x0076c
B33: 00IPL #5 | E33: あなたはなぜ、ここクライツェンに？ | F33: =LEN(E33) | G33: "What are you doing here in Kreitzen?" | H33: =LEN(G33) | J33: 00IPL.SCN | K33: 0x0077e
B34: 00IPL #5 | F34: =LEN(E34) | G34: [BLANK] | H34: =LEN(G34) | J34: 00IPL.SCN | K34: 0x007af
B35: 00IPL #5 | E35: 剣の修行の旅をしている。 | F35: =LEN(E35) | G35: "I'm journeying to improve my sword skills, | H35: =LEN(G35) | J35: 00IPL.SCN | K35: 0x007c6
B36: 00IPL #5 | F36: =LEN(E36) | G36: [BLANK] | H36: =LEN(G36) | J36: 00IPL.SCN | K36: 0x007e6
B37: 00IPL #5 | E37: 別にここでなくても、かまわなかったんだが・・・ | F37: =LEN(E37) | G37: I just ended up in Kreitzen, any place would have been fine." | H37: =LEN(G37) | J37: 00IPL.SCN | K37: 0x007f2
B38: 00IPL #5 | F38: =LEN(E38) | G38: [BLANK] | H38: =LEN(G38) | J38: 00IPL.SCN | K38: 0x0082f
B39: 00IPL #5 | E39: 剣を極めた後、あなたは何を成すつもりか？ | F39: =LEN(E39) | G39: "And what will you do once you've mastered the blade?" | H39: =LEN(G39) | J39: 00IPL.SCN | K39: 0x0083e
B40: 00IPL #5 | F40: =LEN(E40) | G40: [BLANK] | H40: =LEN(G40) | J40: 00IPL.SCN | K40: 0x00875
B41: 00IPL #5 | E41: ・・・おれはまだ修行中の身だ。 | F41: =LEN(E41) | G41: "...I'm only just a trainee. | H41: =LEN(G41) | J41: 00IPL.SCN | K41: 0x00889
B42: 00IPL #5 | F42: =LEN(E42) | G42: [BLANK] | H42: =LEN(G42) | J42: 00IPL.SCN | K42: 0x008af
B43: 00IPL #5 | E43: 何を成すか、など・・・ | F43: =LEN(E43) | G43: I... don't really know..." | H43: =LEN(G43) | J43: 00IPL.SCN | K43: 0x008c7
B44: 00IPL #5 | F44: =LEN(E44) | G44: [BLANK] | H44: =LEN(G44) | J44: 00IPL.SCN | K44: 0x008ec
B45: 00IPL #5 | E45: しかし、あなたはクライツェンを選んだ・・・ | F45: =LEN(E45) | G45: "Hmm... but you chose Kreitzen. | H45: =LEN(G45) | J45: 00IPL.SCN | K45: 0x008fa
B46: 00IPL #5 | F46: =LEN(E46) | G46: [BLANK] | H46: =LEN(G46) | J46: 00IPL.SCN | K46: 0x0092c
B47: 00IPL #5 | E47: 選ぶという行為に偶然はあり得ません。 | F47: =LEN(E47) | G47: There can be no coincidence in that choice." | H47: =LEN(G47) | J47: 00IPL.SCN | K47: 0x0093d
B48: 00IPL #5 | F48: =LEN(E48) | G48: [BLANK] | H48: =LEN(G48) | J48: 00IPL.SCN | K48: 0x00970
B49: 00IPL #5 | E49: 呪い師らしい物言いだな・・・ | F49: =LEN(E49) | G49: "Maybe I'm just cursed... | H49: =LEN(G49) | J49: 00IPL.SCN | K49: 0x00985
B50: 00IPL #5 | F50: =LEN(E50) | G50: [BLANK] | H50: =LEN(G50) | J50: 00IPL.SCN | K50: 0x009a9
B51: 00IPL #5 | E51: では、逆に尋ねたい。 | F51: =LEN(E51) | G51: Alright then, let's reverse the question. | H51: =LEN(G51) | J51: 00IPL.SCN | K51: 0x009c2
B52: 00IPL #5 | F52: =LEN(E52) | G52: [BLANK] | H52: =LEN(G52) | J52: 00IPL.SCN | K52: 0x009de
B53: 00IPL #5 | E53: お前は、おれの行くべき道を、この魔鏡に映せるか？ | F53: =LEN(E53) | G53: What does that magic mirror of yours suggest I do?" | H53: =LEN(G53) | J53: 00IPL.SCN | K53: 0x009e9
B54: 00IPL #5 | F54: =LEN(E54) | G54: [BLANK] | H54: =LEN(G54) | J54: 00IPL.SCN | K54: 0x00a28
B55: 00IPL #5 | E55: 運命の織り糸は、自らが選ぶもの・・・ | F55: =LEN(E55) | G55: "The threads of fate move to your will. | H55: =LEN(G55) | J55: 00IPL.SCN | K55: 0x00a39
B56: 00IPL #5 | E56: 何が映し出されても、それはあなた自身が望んだものだということを | F56: =LEN(E56) | G56: Anything your mind desires can be projected into reality. | H56: =LEN(G56) | J56: 00IPL.SCN | K56: 0x00a69
B57: 00IPL #5 | F57: =LEN(E57) | G57: [BLANK] | H57: =LEN(G57) | J57: 00IPL.SCN | K57: 0x00aaf
B58: 00IPL #5 | E58: お忘れなきように。 | F58: =LEN(E58) | G58: Don't ever forget that." | H58: =LEN(G58) | J58: 00IPL.SCN | K58: 0x00ac9
B59: 00IPL #5 | F59: =LEN(E59) | G59: [BLANK] | H59: =LEN(G59) | J59: 00IPL.SCN | K59: 0x00aea
B60: 00IPL #5 | E60: よかろう | F60: =LEN(E60) | G60: ...Alright. I won't forget. | H60: =LEN(G60) | J60: 00IPL.SCN | K60: 0x00b09
B61: 99CMN #1 | E61: 鍵がかかっている。 | F61: =LEN(E61) | H61: =LEN(G61) | J61: 99CMN.SCN | K61: 0x007ea
B62: 99CMN #2 | E62: はこれ以上持てない。 | F62: =LEN(E62) | H62: =LEN(G62) | J62: 99CMN.SCN | K62: 0x00841
B63: 99CMN #3 | E63: これ以上のお金は持てない。 | F63: =LEN(E63) | H63: =LEN(G63) | J63: 99CMN.SCN | K63: 0x008ac
B64: 99CMN #4 | E64: ＹＥＳ | F64: =LEN(E64) | H64: =LEN(G64) | J64: 99CMN.SCN | K64: 0x0097b
B65: 99CMN #4 | E65: ＮＯ | F65: =LEN(E65) | H65: =LEN(G65) | J65: 99CMN.SCN | K65: 0x00982
B66: 99CMN #4 | E66: ＹＥＳ | F66: =LEN(E66) | H66: =LEN(G66) | J66: 99CMN.SCN | K66: 0x009b8
B67: 99CMN #4 | E67: ＮＯ | F67: =LEN(E67) | H67: =LEN(G67) | J67: 99CMN.SCN | K67: 0x009bf
B68: 99CMN #5 | E68: を手にいれた。 | F68: =LEN(E68) | H68: =LEN(G68) | J68: 99CMN.SCN | K68: 0x00c6c
A69: Port Albein | B69: 02OLB #1 | E69: 港町オールバイン | F69: =LEN(E69) | G69: Port Albein | H69: =LEN(G69) | J69: 02OLB.SCN | K69: 0x001e5
A70: Port Albein | B70: 02OLB00A #1 | C70: Shinobu -> Innes / ='Names + Places'!C2 | E70: シノブ | F70: =LEN(E70) | G70: Shinobu | H70: =LEN(G70) | J70: 02OLB00A.SCN | K70: 0x00040
A71: Port Albein | B71: 02OLB00A #1 | C71: Shinobu -> Innes / ='Names + Places'!C2 | E71: 「・・・ん？ | F71: =LEN(E71) | G71: Unh... | H71: =LEN(G71) | J71: 02OLB00A.SCN | K71: 0x0004b
A72: Port Albein | B72: 02OLB00A #1 | C72: Shinobu -> Innes / ='Names + Places'!C2 | E72: ・・・あれ？ | F72: =LEN(E72) | G72: ...huh? | H72: =LEN(G72) | J72: 02OLB00A.SCN | K72: 0x00059
A73: Port Albein | B73: 02OLB00A #1 | C73: Shinobu -> Innes / ='Names + Places'!C2 | E73: ・・・・・・なにこれ！？」 | F73: =LEN(E73) | G73: Whoa, what's going on!? | H73: =LEN(G73) | J73: 02OLB00A.SCN | K73: 0x00067
A74: Port Albein | B74: 02OLB00A #1 | C74: Innes -> Shinobu / ='Names + Places'!C2 | E74: エニス | F74: =LEN(E74) | G74: Innes | H74: =LEN(G74) | J74: 02OLB00A.SCN | K74: 0x0008a
A75: Port Albein | B75: 02OLB00A #1 | C75: Innes -> Shinobu / ='Names + Places'!C2 | E75: 「言葉、わかるかい？ | F75: =LEN(E75) | G75: Can you understand me, cutie? | H75: =LEN(G75) | J75: 02OLB00A.SCN | K75: 0x00095
A76: Port Albein | B76: 02OLB00A #1 | C76: Innes -> Shinobu / ='Names + Places'!C2 | E76: あんた異国のヒトだろ？」 | F76: =LEN(E76) | G76: Are you from another kingdom? | H76: =LEN(G76) | J76: 02OLB00A.SCN | K76: 0x000ab
A77: Port Albein | B77: 02OLB00A #1 | C77: ='Names + Places'!C2 -> Shinobu / Innes | E77: シノブ | F77: =LEN(E77) | G77: ='Names + Places'!C2 | H77: =LEN(G77) | J77: 02OLB00A.SCN | K77: 0x000d3
A78: Port Albein | B78: 02OLB00A #1 | C78: ='Names + Places'!C2 -> Shinobu / Innes | E78: 「あ、あなたは？」 | F78: =LEN(E78) | G78: Wh- who the heck are you? | H78: =LEN(G78) | J78: 02OLB00A.SCN | K78: 0x000de
A79: Port Albein | B79: 02OLB00A #1 | C79: ='Names + Places'!C4 -> Shinobu / Innes | E79: エニス | F79: =LEN(E79) | G79: ='Names + Places'!C4 | H79: =LEN(G79) | J79: 02OLB00A.SCN | K79: 0x000f9
A80: Port Albein | B80: 02OLB00A #1 | C80: ='Names + Places'!C4 -> Shinobu / Innes | E80: 「大丈夫みたいだね・・・ | F80: =LEN(E80) | G80: Well, you certainly look lovel- ...lively enough. | H80: =LEN(G80) | J80: 02OLB00A.SCN | K80: 0x00104
A81: Port Albein | B81: 02OLB00A #1 | C81: ='Names + Places'!C4 -> Shinobu / Innes | E81: あたしはエニス、あんたの命の恩人ってわけさ」 | F81: =LEN(E81) | G81: I'm Innes, the person who saved your life. | H81: =LEN(G81) | J81: 02OLB00A.SCN | K81: 0x0011e
A82: Port Albein | B82: 02OLB00A #1 | C82: ='Names + Places'!C2 -> Shinobu / Innes | E82: シノブ | F82: =LEN(E82) | G82: ='Names + Places'!C2 | H82: =LEN(G82) | J82: 02OLB00A.SCN | K82: 0x00156
A83: Port Albein | B83: 02OLB00A #1 | C83: ='Names + Places'!C2 -> Shinobu / Innes | E83: 「ここはどこなの？ | F83: =LEN(E83) | G83: What is this place? | H83: =LEN(G83) | J83: 02OLB00A.SCN | K83: 0x00161
A84: Port Albein | B84: 02OLB00A #1 | C84: ='Names + Places'!C2 -> Shinobu / Innes | E84: 確か、あの時 船が・・・」 | F84: =LEN(E84) | G84: Before, on the ship... | H84: =LEN(G84) | J84: 02OLB00A.SCN | K84: 0x00175
A85: Port Albein | B85: 02OLB00A #1 | C85: ='Names + Places'!C4 -> Shinobu / Innes | E85: エニス | F85: =LEN(E85) | G85: ='Names + Places'!C4 | H85: =LEN(G85) | J85: 02OLB00A.SCN | K85: 0x0019b
A86: Port Albein | B86: 02OLB00A #1 | C86: ='Names + Places'!C4 -> Shinobu / Innes | E86: 「放っといたら、今頃、魔物の餌になってたかもね？」 | F86: =LEN(E86) | G86: Hey, I could have left you out there to be monster snacks, you know? | H86: =LEN(G86) | J86: 02OLB00A.SCN | K86: 0x001a6
A87: Port Albein | B87: 02OLB00A #1 | C87: ='Names + Places'!C2 -> Shinobu / Innes | E87: シノブ | F87: =LEN(E87) | G87: ='Names + Places'!C2 | H87: =LEN(G87) | J87: 02OLB00A.SCN | K87: 0x001e1
A88: Port Albein | B88: 02OLB00A #1 | C88: ='Names + Places'!C2 -> Shinobu / Innes | E88: 「・・・あなたが助けてくれたの？」 | F88: =LEN(E88) | G88: So... you rescued me? | H88: =LEN(G88) | J88: 02OLB00A.SCN | K88: 0x001ec
A89: Port Albein | B89: 02OLB00A #1 | C89: ='Names + Places'!C4 -> Shinobu / Innes | E89: エニス | F89: =LEN(E89) | G89: ='Names + Places'!C4 | H89: =LEN(G89) | J89: 02OLB00A.SCN | K89: 0x00217
A90: Port Albein | B90: 02OLB00A #1 | C90: ='Names + Places'!C4 -> Shinobu / Innes | E90: 「そういうこと」 | F90: =LEN(E90) | G90: You betcha. | H90: =LEN(G90) | J90: 02OLB00A.SCN | K90: 0x00222
A91: Port Albein | B91: 02OLB00A #1 | C91: ='Names + Places'!C2 -> Shinobu / Innes | E91: シノブ | F91: =LEN(E91) | G91: ='Names + Places'!C2 | H91: =LEN(G91) | J91: 02OLB00A.SCN | K91: 0x0023b
A92: Port Albein | B92: 02OLB00A #1 | C92: ='Names + Places'!C2 -> Shinobu / Innes | E92: 「・・・・・・」 | F92: =LEN(E92) | G92: ... | H92: =LEN(G92) | J92: 02OLB00A.SCN | K92: 0x00246
A93: Port Albein | B93: 02OLB00A #1 | C93: ='Names + Places'!C4 -> Shinobu / Innes | E93: エニス | F93: =LEN(E93) | G93: ='Names + Places'!C4 | H93: =LEN(G93) | J93: 02OLB00A.SCN | K93: 0x0025f
A94: Port Albein | B94: 02OLB00A #1 | C94: ='Names + Places'!C4 -> Shinobu / Innes | E94: 「礼はいらないよ」 | F94: =LEN(E94) | G94: Eh, no need to thank me. | H94: =LEN(G94) | J94: 02OLB00A.SCN | K94: 0x0026a
A95: Port Albein | B95: 02OLB00A #1 | C95: ='Names + Places'!C2 -> Shinobu / Innes | E95: シノブ | F95: =LEN(E95) | G95: ='Names + Places'!C2 | H95: =LEN(G95) | J95: 02OLB00A.SCN | K95: 0x00285
A96: Port Albein | B96: 02OLB00A #1 | C96: ='Names + Places'!C2 -> Shinobu / Innes | E96: 「でも、そんな・・・」 | F96: =LEN(E96) | G96: Yes, but... | H96: =LEN(G96) | J96: 02OLB00A.SCN | K96: 0x00290
A97: Port Albein | B97: 02OLB00A #1 | C97: ='Names + Places'!C4 -> Shinobu / Innes | E97: エニス | F97: =LEN(E97) | G97: ='Names + Places'!C4 | H97: =LEN(G97) | J97: 02OLB00A.SCN | K97: 0x002af
A98: Port Albein | B98: 02OLB00A #1 | C98: ='Names + Places'!C4 -> Shinobu / Innes | E98: 「そのかわり、仕事をしてもらおうかな」 | F98: =LEN(E98) | G98: Look cutie, if you want to repay me, why not work for me instead? | H98: =LEN(G98) | J98: 02OLB00A.SCN | K98: 0x002ba
A99: Port Albein | B99: 02OLB00A #1 | C99: ='Names + Places'!C2 -> Shinobu / Innes | E99: シノブ | F99: =LEN(E99) | G99: ='Names + Places'!C2 | H99: =LEN(G99) | J99: 02OLB00A.SCN | K99: 0x002e9
A100: Port Albein | B100: 02OLB00A #1 | C100: ='Names + Places'!C2 -> Shinobu / Innes | E100: 「えッ？ なにそれ？」 | F100: =LEN(E100) | G100: Wait, what?? | H100: =LEN(G100) | J100: 02OLB00A.SCN | K100: 0x002f4
...

Sheet BSDs
A1: Filename | B1: Offset | C1: Japanese | D1: JP_len | E1: English | F1: EN_len | G1: Comments
A2: C020_X10.BSD | B2: 0x00218 | C2: シノブ | D2: 29 | E2: Shinobu | F2: 0
A3: C020_X10.BSD | B3: 0x0023a | C3: 「逃げられない？！」 | D3: 22 | F3: 0
A4: C020_X10.BSD | B4: 0x00283 | C4: カイエス | D4: 28 | E4: Keiuss | F4: 0
A5: C020_X10.BSD | B5: 0x002a5 | C5: 「逃げられんようだな・・・」 | D5: 18 | F5: 0
A6: C021_X10.BSD | B6: 0x0028a | C6: シノブ | D6: 29 | E6: Shinobu | F6: 0
A7: C021_X10.BSD | B7: 0x002ac | C7: 「逃げられない？！」 | D7: 22 | F7: 0
A8: C021_X10.BSD | B8: 0x002f5 | C8: カイエス | D8: 28 | E8: Keiuss | F8: 0
A9: C021_X10.BSD | B9: 0x00317 | C9: 「逃げられんようだな・・・」 | D9: 18 | F9: 0
A10: C021_X10.BSD | B10: 0x00460 | C10: ゼフュードル | D10: 6 | E10: Zerfuedel | F10: 0
A11: C021_X10.BSD | B11: 0x0046e | C11: 「意外と、やるじゃねえか？ | D11: 13 | F11: 0
A12: C021_X10.BSD | B12: 0x0048a | C12: だがよ、そんなナマクラな剣で、 | D12: 16 | F12: 0
A13: C021_X10.BSD | B13: 0x004ac | C13: おれに立ち向かったのが間違いだ | D13: 16 | F13: 0
A14: C021_X10.BSD | B14: 0x004ce | C14: ったな？ この《征嵐剣》の力を | D14: 16 | F14: 0
A15: C021_X10.BSD | B15: 0x004f0 | C15: 見せてやるぜ！」 | D15: 9 | F15: 0
A16: C021_X10.BSD | B16: 0x006ae | C16: ゼフュードル | D16: 6 | E16: Zerfuedel | F16: 0
A17: C021_X10.BSD | B17: 0x006bc | C17: 「一昨日きやがれ！！」 | D17: 11 | F17: 0
A18: C021_X10.BSD | B18: 0x006fb | C18: ゼフュードル | D18: 6 | E18: Zerfuedel | F18: 0
A19: C021_X10.BSD | B19: 0x00709 | C19: 「へっ、《餓嵐》の味はどうだ？」 | D19: 16 | F19: 0
A20: C021_X10.BSD | B20: 0x00752 | C20: カイエス | D20: 4 | E20: Keiuss | F20: 0
A21: C021_X10.BSD | B21: 0x0075c | C21: 「その技・・・ | D21: 7 | F21: 0
A22: C021_X10.BSD | B22: 0x0076c | C22: 自ら編み出したのか？」 | D22: 12 | F22: 0
A23: C021_X10.BSD | B23: 0x007ad | C23: ゼフュードル | D23: 6 | E23: Zerfuedel | F23: 0
A24: C021_X10.BSD | B24: 0x007bb | C24: 「まあ、な。 | D24: 6 | F24: 0
A25: C021_X10.BSD | B25: 0x007c9 | C25: ただ、あんまり無茶な技なんで、 | D25: 16 | F25: 0
A26: C021_X10.BSD | B26: 0x007eb | C26: この《征嵐剣》以外の剣じゃ、で | D26: 16 | F26: 0
A27: C021_X10.BSD | B27: 0x0080d | C27: きねぇがよ。」 | D27: 8 | F27: 0
A28: C021_X10.BSD | B28: 0x00846 | C28: カイエス | D28: 4 | E28: Keiuss | F28: 0
A29: C021_X10.BSD | B29: 0x00850 | C29: 「・・・さすがだ」 | D29: 9 | F29: 0
A30: C021_X10.BSD | B30: 0x0088b | C30: ゼフュードル | D30: 6 | E30: Zerfuedel | F30: 0
A31: C021_X10.BSD | B31: 0x00899 | C31: 「ま、おれは天才だからな」 | D31: 13 | F31: 0
A32: C021_X10.BSD | B32: 0x008dc | C32: カイエス | D32: 4 | E32: Keiuss | F32: 0
A33: C021_X10.BSD | B33: 0x008e6 | C33: 「師匠も、お前の天賦の才は認めて | D33: 16 | F33: 0
A34: C021_X10.BSD | B34: 0x00908 | C34: いた・・・」 | D34: 7 | F34: 0
A35: C021_X10.BSD | B35: 0x0093f | C35: ゼフュードル | D35: 6 | E35: Zerfuedel | F35: 0
A36: C021_X10.BSD | B36: 0x0094d | C36: 「そのくせに、奥義はてめぇに譲ろ | D36: 16 | F36: 0
A37: C021_X10.BSD | B37: 0x0096f | C37: うってんだからなぁ。 | D37: 11 | F37: 0
A38: C021_X10.BSD | B38: 0x00987 | C38: あのもうろくじじいが・・・ | D38: 14 | F38: 0
A39: C021_X10.BSD | B39: 0x009a5 | C39: ・・・ま、残念だったな、おい？ | D39: 16 | F39: 0
A40: C021_X10.BSD | B40: 0x009c7 | C40: てめえの負けだ」 | D40: 9 | F40: 0
A41: C021_X10.BSD | B41: 0x00a02 | C41: カイエス | D41: 4 | E41: Keiuss | F41: 0
A42: C021_X10.BSD | B42: 0x00a0c | C42: 「・・・・・・」 | D42: 8 | E42: ... | F42: 0
A43: C021_X10.BSD | B43: 0x00a45 | C43: ゼフュードル | D43: 6 | E43: Zerfuedel | F43: 0
A44: C021_X10.BSD | B44: 0x00a53 | C44: 「約束通り、奥義の《口伝》をしゃ | D44: 16 | F44: 0
A45: C021_X10.BSD | B45: 0x00a75 | C45: べってもらおーかい！」 | D45: 12 | F45: 0
A46: C021_X10.BSD | B46: 0x00ab6 | C46: シノブ | D46: 3 | E46: Shinobu | F46: 0
A47: C021_X10.BSD | B47: 0x00abe | C47: 「待って！ | D47: 5 | F47: 0
A48: C021_X10.BSD | B48: 0x00aca | C48: そんなの卑怯よ！」 | D48: 10 | F48: 0
A49: C021_X10.BSD | B49: 0x00b07 | C49: ゼフュードル | D49: 6 | E49: Zerfuedel | F49: 0
A50: C021_X10.BSD | B50: 0x00b15 | C50: 「なんだと？ | D50: 6 | F50: 0
A51: C021_X10.BSD | B51: 0x00b23 | C51: てめーは後で遊んでやるから引っ | D51: 16 | F51: 0
A52: C021_X10.BSD | B52: 0x00b45 | C52: こんでろ！」 | D52: 7 | F52: 0
A53: C021_X10.BSD | B53: 0x00b7c | C53: シノブ | D53: 3 | E53: Shinobu | F53: 0
A54: C021_X10.BSD | B54: 0x00b84 | C54: 「そうはいかないわ！ | D54: 10 | F54: 0
A55: C021_X10.BSD | B55: 0x00b9a | C55: 今の闘いは何？ | D55: 8 | F55: 0
A56: C021_X10.BSD | B56: 0x00bac | C56: 実力の差じゃなく、剣の差で勝負 | D56: 16 | F56: 0
A57: C021_X10.BSD | B57: 0x00bce | C57: がついたなんて、おかしいわよ！」 | D57: 17 | F57: 0
A58: C021_X10.BSD | B58: 0x00c19 | C58: ゼフュードル | D58: 6 | E58: Zerfuedel | F58: 0
A59: C021_X10.BSD | B59: 0x00c27 | C59: 「ケチつける気か？ | D59: 9 | F59: 0
A60: C021_X10.BSD | B60: 0x00c3b | C60: 勝ちは勝ちだぜ」 | D60: 9 | F60: 0
A61: C021_X10.BSD | B61: 0x00c76 | C61: シノブ | D61: 3 | E61: Shinobu | F61: 0
A62: C021_X10.BSD | B62: 0x00c7e | C62: 「もし、カイエスがあなたと同じぐ | D62: 16 | F62: 0
A63: C021_X10.BSD | B63: 0x00ca0 | C63: らい強い剣を持ってたとしたら？」 | D63: 17 | F63: 0
A64: C021_X10.BSD | B64: 0x00ceb | C64: ゼフュードル | D64: 6 | E64: Zerfuedel | F64: 0
A65: C021_X10.BSD | B65: 0x00cf9 | C65: 「なにィ？ | D65: 5 | F65: 0
A66: C021_X10.BSD | B66: 0x00d05 | C66: ・・・何が言いたいンだ？」 | D66: 14 | F66: 0
A67: C021_X10.BSD | B67: 0x00d4a | C67: シノブ | D67: 3 | E67: Shinobu | F67: 0
A68: C021_X10.BSD | B68: 0x00d52 | C68: 「あなたも偉そうにしてる割には、 | D68: 16 | F68: 0
A69: C021_X10.BSD | B69: 0x00d74 | C69: 剣の力に頼りっぱなしだってこと | D69: 16 | F69: 0
A70: C021_X10.BSD | B70: 0x00d96 | C70: よ！ | D70: 4 | F70: 0
A71: C021_X10.BSD | B71: 0x00da0 | C71: そんなの剣士じゃないわね！」 | D71: 15 | F71: 0
A72: C021_X10.BSD | B72: 0x00de7 | C72: ゼフュードル | D72: 6 | E72: Zerfuedel | F72: 0
A73: C021_X10.BSD | B73: 0x00df5 | C73: 「へっ、へへへへへっ！ こいつァ | D73: 16 | F73: 0
A74: C021_X10.BSD | B74: 0x00e17 | C74: いいや！ おもしれェ！ | D74: 12 | F74: 0
A75: C021_X10.BSD | B75: 0x00e31 | C75: おれを挑発しようってかァ？」 | D75: 15 | F75: 0
A76: C021_X10.BSD | B76: 0x00e78 | C76: シノブ | D76: 3 | E76: Shinobu | F76: 0
A77: C021_X10.BSD | B77: 0x00e80 | C77: 「ホントの事を言っているだけでし | D77: 16 | F77: 0
A78: C021_X10.BSD | B78: 0x00ea2 | C78: ょ！」 | D78: 4 | F78: 0
A79: C021_X10.BSD | B79: 0x00ed3 | C79: カイエス | D79: 4 | E79: Keiuss | F79: 0
A80: C021_X10.BSD | B80: 0x00edd | C80: 「・・・やめろ、シノブ。 | D80: 12 | F80: 0
A81: C021_X10.BSD | B81: 0x00ef7 | C81: 剣士の戦いに剣の優劣など、関係 | D81: 16 | F81: 0
A82: C021_X10.BSD | B82: 0x00f19 | C82: ない」 | D82: 4 | F82: 0
A83: C021_X10.BSD | B83: 0x00f4a | C83: ゼフュードル | D83: 6 | E83: Zerfuedel | F83: 0
A84: C021_X10.BSD | B84: 0x00f58 | C84: 「へ、言うじゃねぇか？ | D84: 11 | F84: 0
A85: C021_X10.BSD | B85: 0x00f70 | C85: だがよ、確かに、この《征嵐剣》 | D85: 16 | F85: 0
A86: C021_X10.BSD | B86: 0x00f92 | C86: は特別すぎたかもしれねぇな？」 | D86: 16 | F86: 0
A87: C021_X10.BSD | B87: 0x00fdb | C87: ゼフュードル | D87: 6 | E87: Zerfuedel | F87: 0
A88: C021_X10.BSD | B88: 0x00fe9 | C88: 「・・・・・・ | D88: 7 | F88: 0
A89: C021_X10.BSD | B89: 0x00ff9 | C89: いいだろう、勝負は預けておいて | D89: 16 | F89: 0
A90: C021_X10.BSD | B90: 0x0101b | C90: やるぜ」 | D90: 5 | F90: 0
A91: C021_X10.BSD | B91: 0x0104e | C91: ゼフュードル | D91: 6 | E91: Zerfuedel | F91: 0
A92: C021_X10.BSD | B92: 0x0105c | C92: 「カイエス、よく聞け！ | D92: 11 | F92: 0
A93: C021_X10.BSD | B93: 0x01074 | C93: バルクルーサ城のある場所に、こ | D93: 16 | F93: 0
A94: C021_X10.BSD | B94: 0x01096 | C94: の国の宝と呼ばれる剛剣が隠され | D94: 16 | F94: 0
A95: C021_X10.BSD | B95: 0x010b8 | C95: ている」 | D95: 5 | F95: 0
A96: C021_X10.BSD | B96: 0x010eb | C96: ゼフュードル | D96: 6 | E96: Zerfuedel | F96: 0
A97: C021_X10.BSD | B97: 0x010f9 | C97: 「あとでおれがちょうだいしようと | D97: 16 | F97: 0
A98: C021_X10.BSD | B98: 0x0111b | C98: 思ってたんだが、そいつをてめー | D98: 16 | F98: 0
A99: C021_X10.BSD | B99: 0x0113d | C99: にくれてやる！ | D99: 8 | F99: 0
A100: C021_X10.BSD | B100: 0x0114f | C100: もっとも、城に潜り込めたら、の | D100: 16 | F100: 0
...

Sheet BD.BIN
A1: Offset | B1: Japanese | C1: JP_len | D1: English | E1: EN_len | F1: Comments
A2: 0x09e01 | B2: カイエスは | C2: =LEN(B2) | D2: Keiuss gained | E2: =LEN(D1) | F2: Caius got | G2: Is this used for other things besides "got" situations? Such as "Keiuss fell asleep" or "Keiuss has fallen"? | H2: Pretty sure it's just post-battle item/exp/gold/level stuff, but I will check.
A3: 0x09e33 | B3: シノブは | C3: =LEN(B3) | D3: Shinobu gained | E3: =LEN(F2) | F3: Shinobu got | G3: Same as above
A4: 0x09e3d | B4: ptsの経験値を得た。 | C4: =LEN(B4) | D4: EXP. | E4: =LEN(F4) | F4: experience pts.
A5: 0x09e51 | B5: レベルアップした。 | C5: =LEN(B5) | D5: a level! | E5: =LEN(F5) | F5: levelled up.
A6: 0x09ed2 | B6: \f | C6: =LEN(B6) | D6: \f | E6: =LEN(F6) | F6: Gold.
A7: 0x09ed5 | B7: Goldを得た。 | D7: gold taken. | E7: =LEN(F7)
A8: 0x09f2c | B8: を手に入れた。 | C8: =LEN(B8) | D8: received. | E8: =LEN(F8) | F8: .
A9: 0x09f6b | B9: パーティは全滅した。 | C9: =LEN(B9) | D9: Annihilated... | E9: =LEN(F9) | F9: Annihilated... | G9: Too long?
A10: 0x0b1e0 | B10: カイエス | C10: =LEN(B10) | D10: Keiuss | E10: =LEN(F10) | F10: Caius
A11: 0x0b1e9 | B11: シノブ | C11: =LEN(B11) | D11: Shinobu | E11: =LEN(F11) | F11: Shinobu
A12: 0x0b1f0 | B12: シノブ | C12: =LEN(B12) | D12: Shinobu | E12: =LEN(F12) | F12: Shinobu
A13: 0x0ba4a | B13: ステータス | C13: =LEN(B13) | D13: Status | E13: =LEN(F13) | F13: Status
A14: 0x0ba55 | B14: 魔法 | C14: =LEN(B14) | D14: Magic | E14: =LEN(F14) | F14: Magic
A15: 0x0ba5a | B15: 道具 | C15: =LEN(B15) | D15: Item | E15: =LEN(F15) | F15: Item
A16: 0x0ba5f | B16: 装備 | C16: =LEN(B16) | D16: Equipment | E16: =LEN(F16) | F16: Equipment
A17: 0x0ba64 | B17: システム | C17: =LEN(B17) | D17: System | E17: =LEN(F17) | F17: System
A18: 0x0ba6e | B18: ステータス | C18: =LEN(B18) | D18: Status | E18: =LEN(F18) | F18: Status
A19: 0x0ba79 | B19: 道具 | C19: =LEN(B19) | D19: Item | E19: =LEN(F19) | F19: Item
A20: 0x0ba7e | B20: 装備 | C20: =LEN(B20) | D20: Equipment | E20: =LEN(F20) | F20: Equipment
A21: 0x0ba83 | B21: システム | C21: =LEN(B21) | D21: System | E21: =LEN(F21) | F21: System
... A40: 0x0bb16 | B40: 剣士 | C40: =LEN(B40) | D40: Swordsman | E40: =LEN(F40) | F40: Swordsman
A41: 0x0bb1c | B41: 術法士 | C41: =LEN(B41) | D41: Mystic Knight | E41: =LEN(F41) | F41: Artist | G41: This is tougher, means someone with a lot of special techniques for fighting, but implies they're also a knight of a sort.
A42: 0x0bb2d | B42: カイエス・ナインターク | C42: =LEN(B42) | D42: Keiuss Neintauk | E42: =LEN(F42) | F42: Caius Ninthaku
A43: 0x0bb44 | B43: シノブ・リュード | C43: =LEN(B43) | D43: Shinobu Ryudo | E43: =LEN(F43) | F43: Shinobu Ryudo
A44: 0x0bb58 | B44: 正常 | C44: =LEN(B44) | D44: Normal | E44: =LEN(F44) | F44: Normal | G44: Status (As opposed to like poisoned or something)
A45: 0x0bb5d | B45: 攻撃力 | C45: =LEN(B45) | D45: Attack | E45: =LEN(F45) | F45: Attack
A46: 0x0bb64 | B46: 防御力 | C46: =LEN(B46) | D46: Defense | E46: =LEN(F46) | F46: Defense
A47: 0x0bb6b | B47: 魔法攻撃力 | C47: =LEN(B47) | D47: Mg. Attack | E47: =LEN(F47) | F47: Ma. Attack
A48: 0x0bb76 | B48: 魔法防御力 | C48: =LEN(B48) | D48: Mg. Defense | E48: =LEN(F48) | F48: Ma. Defense
A49: 0x0bb81 | B49: 命中力 | C49: =LEN(B49) | D49: Accuracy | E49: =LEN(F49) | F49: Accuracy
A50: 0x0bb88 | B50: 回避力 | C50: =LEN(B50) | D50: Evasion | E50: =LEN(F50) | F50: Evasion
A51: 0x0bb8f | B51: 素早さ | C51: =LEN(B51) | D51: Speed | E51: =LEN(F51) | F51: Speed
A52: 0x0bb96 | B52: 武器 | C52: =LEN(B52) | D52: Weapon | E52: =LEN(F52) | F52: Weapon
A53: 0x0bb9b | B53: 防具 | C53: =LEN(B53) | D53: Armor | E53: =LEN(F53) | F53: Armor
A54: 0x0bba0 | B54: ｱｲﾃﾑ 1 | C54: =LEN(B54) | D54: Acc. 1 | E54: =LEN(F54) | F54: Item 1
A55: 0x0bbac | B55: ｱｲﾃﾑ 2 | C55: =LEN(B55) | D55: Acc. 2 | E55: =LEN(F55) | F55: Item 2
A56: 0x0bbbe | B56: 【 剣技 】 | C56: =LEN(B56) | D56: [Sword Techs] | E56: =LEN(F56) | F56: [Sword Techs]
... A94: 0x0e78a | B94: ＬＣＤ８階調 | C94: =LEN(B94) | D94: 8-shade LCD | E94: =LEN(F94) | F94: LCD 8

Sheet ITEM.SMI
A1: Offset | B1: Japanese | C1: JP_len | D1: English | E1: EN_len | F1: Description | G1: Comments
A2: 0x02bfc | B2: Ｄｕｍｍｙ | C2: =LEN(B2) | E2: =LEN(D2) | F2: Ｎｏｎｅ
A3: 0x02c07 | B3: 薬草 | C3: =LEN(B3) | D3: Herbs | E3: =LEN(D3) | F3: ＨＰを２００Ｐ回復する
A4: 0x02c0c | B4: ポーション | C4: =LEN(B4) | D4: Potion | E4: =LEN(D4) | F4: ＨＰを５００Ｐ回復する
A5: 0x02c17 | B5: ハイポーション | C5: =LEN(B5) | D5: High Potion | E5: =LEN(D5) | F5: ＨＰを１０００Ｐ回復する | H5: High Potion | I5: Strong Potion | J5: Mega Potion
A6: 0x02c26 | B6: エリクサー | C6: =LEN(B6) | D6: Elixir | E6: =LEN(D6) | F6: ＨＰ・ＭＰを完全回復する
A7: 0x02c31 | B7: 風船草 | C7: =LEN(B7) | E7: =LEN(D7) | F7: 眠りから覚ます | H7: Balloon Grass | J7: Balloon Weed | K7: Balloon Weed | L7: Wake-Up Weed
A8: 0x02c38 | B8: 毒消し | C8: =LEN(B8) | D8: Antidote | E8: =LEN(D8) | F8: 解毒薬
A9: 0x02c3f | B9: テンダーオイル | C9: =LEN(B9) | D9: Tender Oil | E9: =LEN(D9) | F9: 麻痺の治療をする | G9: Cures Paralysis
A10: 0x02c4e | B10: ムーンハーブ | C10: =LEN(B10) | D10: Lunar Herb | E10: =LEN(D10) | F10: 眠り・毒・麻痺および、魔法の影響を打ち消す
A11: 0x02c5b | B11: 気付け薬 | C11: =LEN(B11) | D11: Smelling Salts | E11: =LEN(D11) | F11: 気絶を治療し ＨＰをある程度回復する
A12: 0x02c64 | B12: 崩呪香 | C12: =LEN(B12) | D12: Purifying Incense | E12: =LEN(D12) | F12: 禁止状態の解除をする香木
A13: 0x02c6b | B13: エーテル | C13: =LEN(B13) | D13: Ether | E13: =LEN(D13) | F13: ＭＰ３００Ｐ回復する
A14: 0x02c74 | B14: エーテルプラス | C14: =LEN(B14) | D14: Ether Plus | E14: =LEN(D14) | F14: ＭＰ１０００Ｐ回復する | H14: Ether Plus | I14: Strong Ether | J14: Mega Ether
A15: 0x02c83 | B15: 沈黙の巻物 | C15: =LEN(B15) | D15: Silencing Scroll | E15: =LEN(D15) | F15: 敵の魔法・技を禁止する力を秘める巻物
A16: 0x02c8e | B16: 守護の巻物 | C16: =LEN(B16) | E16: =LEN(D16) | F16: 敵の物理攻撃を防ぐ力を秘める巻物 | H16: Protection Scroll | I16: Guardian Scroll
A17: 0x02c99 | B17: 月光の粉 | C17: =LEN(B17) | E17: =LEN(D17) | F17: 魔力付与の力を秘める不思議な粉末 | H17: Moonlight Dust | I17: Moonlight Powder
A18: 0x02ca2 | B18: 赤の呪石 | C18: =LEN(B18) | E18: =LEN(D18) | F18: 火の呪力が封じられた石 | H18: Red Curse Stone (Literal)
A19: 0x02cab | B19: 青の呪石 | C19: =LEN(B19) | E19: =LEN(D19) | F19: 氷の呪力が封じられた石 | H19: Blue...
A20: 0x02cb4 | B20: 黄の呪石 | C20: =LEN(B20) | E20: =LEN(D20) | F20: 雷の呪力が封じられた石 | H20: Yellow...
A21: 0x02cbd | B21: 火龍の牙 | C21: =LEN(B21) | E21: =LEN(D21) | F21: 火龍を呼ぶ力を持つ宝石 | H21: Fire Dragon Flame | I21: Flame Dragon Fang | J21: Firewyrm Fang | K21: Flame Drake Fang
A22: 0x02cc6 | B22: 小さな靴 | C22: =LEN(B22) | E22: =LEN(D22) | F22: 巨神を呼ぶ力を持つ魔法の品 | H22: Small Shoes | I22: Giant's Tiny Shoes | J22: Tiny Shoes
A23: 0x02ccf | B23: 天使の矢 | C23: =LEN(B23) | D23: Angel's Arrow | E23: =LEN(D23) | F23: 戦の女神を呼ぶ力を持つ矢
A24: 0x02cd8 | B24: 銀の鈴 | C24: =LEN(B24) | D24: Silver Bell | E24: =LEN(D24) | F24: 敵の攻撃無効化能力を封じる
A25: 0x02cdf | B25: 金の鈴 | C25: =LEN(B25) | D25: Golden Bell | E25: =LEN(D25) | F25: ?
A26: 0x02ce6 | B26: 至福の鈴 | C26: =LEN(B26) | D26: Blissful Bell | E26: =LEN(D26) | F26: ?
A27: 0x02cef | B27: ロングソード | C27: =LEN(B27) | D27: Longsword | E27: =LEN(D27) | F27: 広く普及している 一般的な長剣
A28: 0x02cfc | B28: ブロードソード | C28: =LEN(B28) | D28: Broadsword | E28: =LEN(D28) | F28: 攻撃力は長剣に勝るが 命中率が低い大剣
A29: 0x02d0b | B29: シルバーブレード | C29: =LEN(B29) | D29: Silver Blade | E29: =LEN(D29) | F29: 魔力を秘めた銀で作られた剣
A30: 0x02d1c | B30: 石の王 | C30: =LEN(B30) | D30: Kingstone Blade | E30: =LEN(D30) | F30: 鉱石で作られたの石の剣 | G30: May be an actual stone? Has a high counter rate
A31: 0x02d23 | B31: 逆鱗の剣 | C31: =LEN(B31) | D31: Scale Blade | E31: =LEN(D31) | F31: 竜の逆鱗を剥がして作った剣 怒りのパワーを秘める
A32: 0x02d2c | B32: エグゼキューショナーズ | C32: =LEN(B32) | D32: Executioner | E32: =LEN(D32) | F32: 《屠殺人》の名を持つ剣。強大な攻撃力を誇るが？
A33: 0x02d43 | B33: クリムゾンマスター | C33: =LEN(B33) | D33: Crimson Master | E33: =LEN(D33) | F33: 《深紅の支配者》の名を持つ、炎の魔剣 | G33: Does fire damage
A34: 0x02d56 | B34: ダモクレスソード | C34: =LEN(B34) | D34: Sword of Damocles | E34: =LEN(D34) | F34: 比類ない切れ味を誇り、所有者の各能力を上昇させる秘剣だが？
A35: 0x02d67 | B35: 覇者の剣 | C35: =LEN(B35) | D35: Champion's Sword | E35: =LEN(D35) | F35: 一般に普及した剣では最強の逸品
A36: 0x02d70 | B36: 獅心剣 | C36: =LEN(B36) | D36: Samurai Sword | E36: =LEN(D36) | F36: いにしえの時 黒竜と戦った勇者が携えていた伝説の剣
A37: 0x02d77 | B37: ブレードスターライト | C37: =LEN(B37) | D37: Starlight Blade | E37: =LEN(D37) | F37: 《星の光》の名を持つ神速の魔剣
A38: 0x02d8c | B38: ドーンパープル | C38: =LEN(B38) | D38: Dawn Purple | E38: =LEN(D38) | F38: 《暁の紫》の名を持つ、必中の魔剣 | G38: Appears to be an item, not a weapon
A39: 0x02d9b | B39: 騎士の剣 | C39: =LEN(B39) | D39: Knight's Sword | E39: =LEN(D39) | F39: 騎士のために作られた大剣
A40: 0x02da4 | B40: はやぶさの剣 | C40: =LEN(B40) | D40: Falcon Blade | E40: =LEN(D40) | F40: 攻撃回数を増加させる魔剣 | H40: Hayabusa Sword | I40: Falcon Blade | J40: (Note: Does anybody know the story of Hayabusa???)
A41: 0x02db1 | B41: 黒の剣 | C41: =LEN(B41) | D41: Blade of the Darkness | E41: =LEN(D41) | G41: (Has no ingame description)
A42: 0x02db8 | B42: 寄生虫 | C42: =LEN(B42) | E42: =LEN(D42) | F42: ? | G42: This item is equipable by both, and may not be a "weapon" | H42: Parasitic Saber | I42: Vampiric Blade | J42: Soul-Stealer Sword
A43: 0x02dbf | B43: 七星刀 | C43: =LEN(B43) | E43: =LEN(D43) | F43: 刀身に星のような輝点を持つ 魔除けの小刀 | G43: This literally translates as "Seven Star Dagger" but the kanji means "Big Dipper" constellation, and refers to an ancient mystical star worship called Myoken
A44: 0x02dc6 | B44: マジシャンズワンド | C44: =LEN(B44) | D44: Mage's Wand | E44: =LEN(D44) | F44: 魔法使い専用の短杖
A45: 0x02dd9 | B45: シルバーダガー | C45: =LEN(B45) | D45: Silver Dagger | E45: =LEN(D45) | F45: 魔力を秘めた銀で作られた短剣
A46: 0x02de8 | B46: フェザーナイフ | C46: =LEN(B46) | D46: Feather Knife | E46: =LEN(D46) | F46: 使用者の身のこなしを軽くするナイフ
A47: 0x02df7 | B47: ハイドラダガー | C47: =LEN(B47) | D47: Hydra Dagger | E47: =LEN(D47) | F47: ヒドラの骨を加工して作られた短剣
A48: 0x02e06 | B48: エレメンタルダガー | C48: =LEN(B48) | D48: Elemental Dagger | E48: =LEN(D48) | F48: 精霊の力が秘められた短剣
A49: 0x02e19 | B49: 夜半楽 | C49: =LEN(B49) | E49: =LEN(D49) | F49: 蟲毒虫の魔法を使用できる小刀 | G49: This item summons insects to attack | H49: Midnight Song
A50: 0x02e20 | B50: 女帝の短刀 | C50: =LEN(B50) | D50: Empress' Dagger | E50: =LEN(D50) | F50: 一般に普及した小刀では最強の逸品
A51: 0x02e2b | B51: マスターズワンド | C51: =LEN(B51) | D51: Master's Wand | E51: =LEN(D51) | F51: マスタークラスの魔法使い専用の短杖
A52: 0x02e3c | B52: クリスナイフ | C52: =LEN(B52) | D52: Kris | E52: =LEN(D52) | F52: 呪力を高める力を秘めたナイフ 攻撃数がアップする
A53: 0x02e49 | B53: ヘリオドール | C53: =LEN(B53) | D53: Beryl Wand | E53: =LEN(D53) | F53: 魔法の黄水晶で造られた極めて貴重な短杖 | G53: Beryl item of some sort
A54: 0x02e56 | B54: 聖石の宝刀 | C54: =LEN(B54) | E54: =LEN(D54) | F54: 《４つのラピス》が合体した聖なる小刀 魔の力を打ち破る | H54: Sacred Stone | I54: Holy Treasure
A55: 0x02e61 | B55: ハーフプレイト | C55: =LEN(B55) | D55: Half Plate | E55: =LEN(D55) | F55: 広く普及している 一般的な防具
A56: 0x02e70 | B56: ブレストプレイト | C56: =LEN(B56) | D56: Breastplate | E56: =LEN(D56) | F56: ハーフプレイトを改良して防御力を増したもの
A57: 0x02e81 | B57: ゴールドアーマー | C57: =LEN(B57) | D57: Golden Armor | E57: =LEN(D57) | F57: 貴族が作った純金のアーマー。実用性は皆無
A58: 0x02e92 | B58: 騎士の鎧 | C58: =LEN(B58) | D58: Knight's Armor | E58: =LEN(D58) | F58: 騎士たちの装備してる鎧
A59: 0x02e9b | B59: 覇者の鎧 | C59: =LEN(B59) | D59: Champion's Armor | E59: =LEN(D59) | F59: 一般に普及した鎧では最高の逸品
A60: 0x02ea4 | B60: 盾無の鎧 | C60: =LEN(B60) | D60: Shieldless Armor | E60: =LEN(D60) | F60: 盾無用の伝説を持つ異国の鎧 麻痺に耐性がある | G60: Protects from paralysis
A61: 0x02ead | B61: 銀の胸あて | C61: =LEN(B61) | D61: Silver Chestplate | E61: =LEN(D61) | F61: 魔力を秘めた銀で作られた胸あて 魔法防御の効果がある
A62: 0x02eb8 | B62: ブルースケイル | C62: =LEN(B62) | D62: Blue Scale | E62: =LEN(D62) | F62: 水竜の青い鱗で作られた鎧 水の呪力に耐性を持つ | G62: (?)
A63: 0x02ec7 | B63: ブラックレネゲイド | C63: =LEN(B63) | D63: Black Renegade | E63: =LEN(D63) | F63: 《黒い鉱石》を加工して作られた鎧 《黒竜》の波動を防ぐ | G63: (?)
A64: 0x02eda | B64: 不思議なビスチェ | C64: =LEN(B64) | D64: Mysterious Bustier | E64: =LEN(D64) | F64: ＭＰを戦闘中に回復する不思議なビスチェ | G64: (May adjust that to be more clever)
A65: 0x02eeb | B65: 導師のベスト | C65: =LEN(B65) | D65: Guru's Vest | E65: =LEN(D65) | F65: 広く普及した一般的な魔法衣 | H65: Guru's Vest | I65: Wiseman's Vest
A66: 0x02ef8 | B66: 水晶の胸あて | C66: =LEN(B66) | D66: Crystal Chestplate | E66: =LEN(D66) | F66: 普通の水晶をちりばめた胸あて
A67: 0x02f05 | B67: ウィンドチェニック | C67: =LEN(B67) | D67: Wind Tunic | E67: =LEN(D67) | F67: 風耐性、麻痺耐性を持つ魔法衣
A68: 0x02f18 | B68: 紫の法衣 | C68: =LEN(B68) | D68: Purple Robe | E68: =LEN(D68) | F68: 高位の神官が身につける衣。沈黙を防ぐ
A69: 0x02f21 | B69: 白のケープ | C69: =LEN(B69) | D69: White Cape | E69: =LEN(D69) | F69: 魔力を秘めた純白のケープ
A70: 0x02f2c | B70: 女帝の胸あて | C70: =LEN(B70) | D70: Empress' Chestplate | E70: =LEN(D70) | F70: 一般に普及した胸あてでは最強の品 防御力がアップする
A71: 0x02f39 | B71: 妖精の羽衣 | C71: =LEN(B71) | D71: Fairies' Robe | E71: =LEN(D71) | F71: 回避力がアップする魔法衣
A72: 0x02f44 | B72: 月のビスチェ | C72: =LEN(B72) | D72: Moon Bustier | E72: =LEN(D72) | F72: 月の魔力の守護を得る衣。眠りを完全に防ぐ | G72: (May adjust that to be more clever)
A73: 0x02f51 | B73: クリスタルドレス | C73: =LEN(B73) | D73: Crystal Dress | E73: =LEN(D73) | F73: 清浄なる水晶をちりばめた最高の防御力を持つ魔法衣 | G73: (May adjust that to be more clever)
A74: 0x02f62 | B74: 堕天使のコルセット | C74: =LEN(B74) | D74: Fallen Angel's Corset | E74: =LEN(D74) | F74: かつて誰も目にしたことのない幻のコルセット・・・ | G74: (May adjust that to be more clever)
A75: 0x02f75 | B75: 月影の紐 | C75: =LEN(B75) | D75: Moonlight Thread | E75: =LEN(H75) | F75: 月の魔力を織り込んだ紐 | G75: This is an accessory
A76: 0x02f7e | B76: 月影の干物 | C76: =LEN(B76) | D76: Moonlight Threadfin | E76: =LEN(D76) | F76: 身につけると臭い | G76: (This may be a joke item, based on "himo" for rope/thread and "himono" for dried fish)
A77: 0x02f89 | B77: タリスマン | C77: =LEN(B77) | D77: Talisman | E77: =LEN(D77) | F77: 不思議なお守り 回避率・魔法防御がアップする
A78: 0x02f94 | B78: ジルコンチェーン | C78: =LEN(B78) | D78: Zircon Chain | E78: =LEN(D78) | F78: 高い硬度を持つジルコンで作られたチェーン 攻撃力がアップ | H78: Zircon Chain | I78: Zirconium Chain | J78: Zircon Necklace | K78: Zirconium Necklace
A79: 0x02fa5 | B79: 絹のスカーフ | C79: =LEN(B79) | D79: Silk Scarf | E79: =LEN(D79) | F79: シノブの母国でしか売られてないスカーフ
A80: 0x02fb2 | B80: 金の髪飾り | C80: =LEN(B80) | D80: Golden Hairpin | E80: =LEN(D80) | F80: 金をちりばめたおしゃれな髪飾り
A81: 0x02fbd | B81: 雪のリボン | C81: =LEN(B81) | D81: Snow Ribbon | E81: =LEN(D81) | F81: 雪の結晶をかたどったリボン | G81: (May adjust that to be more poetic)
A82: 0x02fc8 | B82: 精霊のスカーフ | C82: =LEN(B82) | D82: Spirit's Scarf | E82: =LEN(D82) | F82: 精霊の守護を得るスカーフ | G82: (May adjust that to be more poetic)
A83: 0x02fd7 | B83: 女帝の髪飾り | C83: =LEN(B83) | D83: Empress' Hairpin | E83: =LEN(D83) | F83: 一般に普及した髪飾りでは最も高価な品
A84: 0x02fe4 | B84: 革手袋 | C84: =LEN(B84) | D84: Leather Gloves | E84: =LEN(D84) | F84: 手のひらを保護する わずかながら防御力が上がる
A85: 0x02feb | B85: ガントレット | C85: =LEN(B85) | D85: Gauntlet | E85: =LEN(D85) | F85: 手元を保護し 攻撃力をアップさせる
A86: 0x02ff8 | B86: 銀のこて | C86: =LEN(B86) | D86: Silver Bracer | E86: =LEN(D86) | F86: 魔力を秘めた銀で作られたこて 魔法防御がアップする
A87: 0x03001 | B87: ドラゴンのこて | C87: =LEN(B87) | D87: Dragon Bracer | E87: =LEN(D87) | F87: ドラゴンの鱗で作られたこて 攻撃力がアップし 火耐性を持つ
A88: 0x03010 | B88: デモンズナックル | C88: =LEN(B88) | D88: Demon's Knuckle | E88: =LEN(D88) | F88: 魔力を秘めたナックル 敵の攻撃にリバーサルで報いる
A89: 0x03021 | B89: 覇者のこて | C89: =LEN(B89) | D89: Champion's Bracer | E89: =LEN(D89) | F89: 軽鎧並みの防御力を誇るこて
A90: 0x0302c | B90: プロテクトリング | C90: =LEN(B90) | D90: Protection Ring | E90: =LEN(D90) | F90: 円盾並みの防御力を持つ魔法の指輪
A91: 0x0303d | B91: 銀の腕輪 | C91: =LEN(B91) | D91: Silver Bracelet | E91: =LEN(D91) | F91: 魔力を秘めた銀で作られた腕輪
A92: 0x03046 | B92: 妖精王の腕輪 | C92: =LEN(B92) | D92: Fairy King's Bracelet | E92: =LEN(D92) | F92: 妖精に魅入られた腕輪 魔法攻撃力・魔法防御力がアップする
A93: 0x03053 | B93: エターナルリング | C93: =LEN(B93) | D93: Eternal Ring | E93: =LEN(D93) | F93: ヒールの魔力が秘められた指輪
A94: 0x03064 | B94: エメラルドリング | C94: =LEN(B94) | D94: Elemental Ring | E94: =LEN(D94) | F94: 非常に高値で取り引きされてる希少な指輪
A95: 0x03075 | B95: 光の腕輪 | C95: =LEN(B95) | D95: Light Bracelet | E95: =LEN(D95) | F95: 不思議な淡い光で包まれた腕輪 | G95: (May adjust that to be more poetic)
A96: 0x0307e | B96: 騎士の紋章 | C96: =LEN(B96) | D96: Knight's Coat of Arms | E96: =LEN(D96) | F96: 戦いに散った騎士たちの思いが込められた紋章 | G96: (May shorten)
A97: 0x03089 | B97: アミュレット | C97: =LEN(B97) | D97: Amulet | E97: =LEN(D97) | F97: 幸せな気分になれるお守り
A98: 0x03096 | B98: スタープラチナ | C98: =LEN(B98) | D98: Platinum Star | E98: =LEN(D98) | F98: 加速の呪力を秘める魔石
A99: 0x030a5 | B99: 水晶のネックレス | C99: =LEN(B99) | D99: Crystal Necklace | E99: =LEN(D99) | F99: 清浄な水晶がついてるネックレス
A100: 0x030b6 | B100: 星屑のティアラ | C100: =LEN(B100) | D100: Stardust Tiara | E100: =LEN(D100) | F100: 祈りの力で総てのパラメーターが少しだけアップする冠
...

Sheet KIES.SMI
A1: Offset | B1: Japanese | C1: JP_len | D1: English | E1: EN_len | F1: Comments
A2: 0x00de1 | B2: 三日月 | C2: =LEN(B2) | E2: =LEN(D2)
A3: 0x00de8 | B3: 滝降 | C3: =LEN(B3) | E3: =LEN(D3)
A4: 0x00ded | B4: 皇狼 | C4: =LEN(B4) | E4: =LEN(D4)
A5: 0x00df2 | B5: 蓮華 | C5: =LEN(B5) | E5: =LEN(D5)
A6: 0x00df7 | B6: 徹し | C6: =LEN(B6) | E6: =LEN(D6)
A7: 0x00dfc | B7: 通背 | C7: =LEN(B7) | E7: =LEN(D7)
A8: 0x00e01 | B8: 地摺 | C8: =LEN(B8) | E8: =LEN(D8)
A9: 0x00e06 | B9: 刃紋 | C9: =LEN(B9) | E9: =LEN(D9)
A10: 0x00e0e | B10: 笹船 | C10: =LEN(B10) | E10: =LEN(D10)
A11: 0x00e13 | B11: 閃歩 | C11: =LEN(B11) | E11: =LEN(D11)
A12: 0x00e18 | B12: 抜け | C12: =LEN(B12) | E12: =LEN(D12)
A13: 0x00e1d | B13: 青竜 | C13: =LEN(B13) | E13: =LEN(D13)
A14: 0x00e22 | B14: ＥＤ居合 | C14: =LEN(B14) | E14: =LEN(D14)

Sheet SHINOBU.SMI
A1: Offset | B1: Japanese | C1: JP_len | D1: English | E1: EN_len | F1: Comments
A2: 0x010ce | B2: バーニングスフィア | C2: =LEN(B2) | E2: =LEN(D2)
A3: 0x010e1 | B3: 火龍召 | C3: =LEN(B3) | E3: =LEN(D3)
A4: 0x010e8 | B4: 符鳥刃 | C4: =LEN(B4) | D4: Bird's Blade | E4: =LEN(D4)
A5: 0x010ef | B5: 風神召 | C5: =LEN(B5) | E5: =LEN(D5)
A6: 0x010f6 | B6: シルバーソーン | C6: =LEN(B6) | E6: =LEN(D6)
A7: 0x01105 | B7: ブルーエレメント | C7: =LEN(B7) | E7: =LEN(D7)
A8: 0x01116 | B8: ターニングプラズマ | C8: =LEN(B8) | E8: =LEN(D8)
A9: 0x01129 | B9: 雷神召 | C9: =LEN(B9) | E9: =LEN(D9)
A10: 0x01130 | B10: アースファング | C10: =LEN(B10) | E10: =LEN(D10)
A11: 0x0113f | B11: 磐舟 | C11: =LEN(B11) | E11: =LEN(D11)
A12: 0x01144 | B12: 巨神召 | C12: =LEN(B12) | E12: =LEN(D12)
A13: 0x0114b | B13: スターレイン | C13: =LEN(B13) | E13: =LEN(D13)
A14: 0x01158 | B14: ワルキューレ | C14: =LEN(B14) | E14: =LEN(D14)
A15: 0x01165 | B15: スーパーボール | C15: =LEN(B15) | E15: =LEN(D15)
A16: 0x01174 | B16: ドリームミスト | C16: =LEN(B16) | E16: =LEN(D16)
... A34: 0x012be | B34: 眠り・毒・麻痺および、魔法の影響を打ち消す | C34: =LEN(B34) | E34: =LEN(D34)

Sheet Names + Places
A1: Source | B1: Japanese | C1: English
B2: シノブ・リュード | C2: Shinobu
B3: カイエス・ナインターク | C3: Keiuss
B4: エニス | C4: Innes
B5: ゴードン | C5: Gordon
B6: ゲンハス | C6: Geinhaas
B7: グラウベン | C7: Grauben
B8: ダンカン | C8: Duncan
B9: マルダー | C9: Marder
B10: ユーバウム | C10: Jubaum
B11: リール | C11: Lilie
B12: ゼフュードル | C12: Zerfuedel
B13: ルルス | C13: Lullus
... B21: ルチア | C21: Lucia
B22: サトー | C22: Satou | D22: Sato (Japanese name?)
B23: ガルサ | C23: Grueser
A25: 02OLB | B25: 港町オールバイン | C25: Port Albein
A26: 03YSK | B26: 貴族の屋敷 | C26: Nobles' Manor
A27: 04OLD | B27: 古い本の洞窟 | C27: Cave of the Ancient Book
A28: 05SKS | B28: 関所 | C28: Border Post
A29: 06BLK | B29: 首都バルクルーサ | C29: Capital City Walkreuz
A30: 07CSL | B30: バルクルーサ城 | C30: Walkreuz Castle
A31: 08CKD | B31: バルクルーサ地下道 | C31: Walkreuz Underground
A32: 09HIK | B32: 廃坑 | C32: Abandoned Mine
A33: 10TNI | B33: 谷間の遺跡 | C33: Valley Ruins
A34: 11STG | B34: 湿原 | C34: Marshlands
A35: 12MRS | B35: 森の島 | C35: Isle of Forests
A36: 13SLP | B36: 眠り姫の洞窟 | D36: Sleeping Beauty Cave | E36: Cave of Slumbers | F36: Cave of the Sleeping Princess
A37: 14YMM | B37: 辺境への山道 | C37: Frontier Pass
A38: 15MKR | B38: マッカロックの町 | D38: City McCulloch | E38: (Scottish?)
A39: 16MKI | B39: マッカロックの遺跡 | D39: Ruins McCulloch
A40: 17DRL | B40: ドラールの村 | C40: Dorral Village
A41: 18KSK | B41: 黒い鉱石の洞窟 | D41: Black Ore Cave | E41: Black Ore Mine (?)
A42: 19IRE | B42: 入り江の村 | D42: Cove-side Village | E42: Bucht Village
A43: 20NNP | B43: 難破船の入り江 | C43: Shipwreck Cove
A44: 21KTI | B44: 湖底 | D44: Lakebed | E44: Lake-floor
A45: 22MZI | B45: 湖の遺跡 | D45: Lakebed Ruins | E45: Lake-floor Ruins
A46: 23SOH | B46: ソーホゥの村 | D46: Soho Village
A47: 24UMB | B47: 海辺の村 | C47: Seaside Village
A48: 25TOU | B48: 貴族の塔 | D48: Lord's Tower | E48: Noble's Tower
A49: 26KKR | B49: 黒竜洞 | D49: Black Dragon Cave | E49: Dark Dragon Cave | F49: Dark Dragon's Den
A50: 27KKI | B50: 黒竜洞の遺跡 | D50: Ruins of the Black Dragon | E50: Ruins of the Black Dragon's Cave | F50: Dark Dragon's Den Ruins
A51: 28KDI | B51: 古代の石室群 | D51: Ancient Stone Chambers | E51: (Note: I want to see this area before committing to this)
A52: 29KNT | B52: 混沌の回廊 | D52: Chaos Cloister | E52: Corridor of Chaos
A53: 30IZM | B53: 聖域の泉 | D53: Fountain of Sacred Waters | E53: Sanctuary of the Fountain | F53: Sanctuary Spring
